[{"id":"84794c68.55217","type":"tab","label":"Flow 14","disabled":false,"info":""},{"id":"27c3214d.1b8ece","type":"countdown","z":"84794c68.55217","name":"","topic":"","payloadTimerStart":"2","payloadTimerStartType":"num","payloadTimerStop":"1","payloadTimerStopType":"num","timer":"3","resetWhileRunning":false,"setTimeToNewWhileRunning":true,"startCountdownOnControlMessage":false,"x":170,"y":280,"wires":[["1fde0ba.604f0f4"],[]]},{"id":"767e9c7e.d4fe64","type":"http request","z":"84794c68.55217","name":"","method":"GET","ret":"txt","paytoqs":"ignore","url":"your_wifimodule_url","tls":"","persist":false,"proxy":"","authType":"","x":330,"y":220,"wires":[["8c99fe88.071f2"]]},{"id":"bd5ef5e8.5b1a48","type":"http request","z":"84794c68.55217","name":"","method":"GET","ret":"txt","paytoqs":"ignore","url":"your_wifimodule_url","tls":"","persist":false,"proxy":"","authType":"","x":530,"y":260,"wires":[[]]},{"id":"8c99fe88.071f2","type":"debug","z":"84794c68.55217","name":"","active":true,"tosidebar":true,"console":false,"tostatus":false,"complete":"false","statusVal":"","statusType":"auto","x":510,"y":140,"wires":[]},{"id":"de85fec1.84144","type":"http in","z":"84794c68.55217","name":"","url":"/command","method":"get","upload":false,"swaggerDoc":"","x":100,"y":120,"wires":[["8c99fe88.071f2","54df3159.4b053","edb19d95.638d4"]]},{"id":"54df3159.4b053","type":"function","z":"84794c68.55217","name":"","func":"if(msg.payload.command==\"DOORON\")\n{\n    msg.payload=1\n}\nelse{\n    msg.payload=0\n}\nreturn msg;","outputs":1,"noerr":0,"initialize":"","finalize":"","libs":[],"x":100,"y":160,"wires":[["d1d7244c.a468a8"]]},{"id":"d1d7244c.a468a8","type":"switch","z":"84794c68.55217","name":"","property":"payload","propertyType":"msg","rules":[{"t":"eq","v":"1","vt":"num"},{"t":"eq","v":"0","vt":"str"}],"checkall":"true","repair":false,"outputs":2,"x":110,"y":200,"wires":[["767e9c7e.d4fe64","27c3214d.1b8ece","5272f678.26c7f8"],["8c99fe88.071f2"]]},{"id":"edb19d95.638d4","type":"http response","z":"84794c68.55217","name":"","statusCode":"","headers":{},"x":330,"y":80,"wires":[]},{"id":"1fde0ba.604f0f4","type":"switch","z":"84794c68.55217","name":"","property":"payload","propertyType":"msg","rules":[{"t":"eq","v":"1","vt":"num"},{"t":"eq","v":"2","vt":"num"}],"checkall":"true","repair":false,"outputs":2,"x":290,"y":340,"wires":[["bd5ef5e8.5b1a48"],[]]},{"id":"a3769e3e.91845","type":"debug","z":"84794c68.55217","name":"","active":true,"tosidebar":true,"console":false,"tostatus":false,"complete":"false","statusVal":"","statusType":"auto","x":530,"y":420,"wires":[]},{"id":"5272f678.26c7f8","type":"function","z":"84794c68.55217","name":"","func":"var now = new Date();\nnow=now.toLocaleString();\na=\"Your door was opened at:-\"\nmsg.payload=a+now\nreturn msg;","outputs":1,"noerr":0,"initialize":"","finalize":"","libs":[],"x":240,"y":420,"wires":[["a3769e3e.91845","cc3ce524.f15478","70848f34.27e4b"]]},{"id":"cc3ce524.f15478","type":"twilio out","z":"84794c68.55217","twilio":"9b1ab9ff.a98a78","twilioType":"sms","url":"","number":"+919800374139","name":"","x":390,"y":480,"wires":[]},{"id":"70848f34.27e4b","type":"cloudant out","z":"84794c68.55217","name":"","cloudant":"","database":"door","service":"node-red-nzdsw-2021--cloudant-1628093501762-94877","payonly":false,"operation":"insert","x":230,"y":520,"wires":[]},{"id":"9b1ab9ff.a98a78","type":"twilio-api","name":"","sid":"AC99f5d556e4f47120b743d8a6b32d361c","from":"+17863218082"}]